nsjwt.py
nsjwt-0.2.1.dist-info/METADATA
nsjwt-0.2.1.dist-info/RECORD
nsjwt-0.2.1.dist-info/WHEEL
nsjwt-0.2.1.dist-info/top_level.txt
