Metadata-Version: 2.1
Name: nsjwt
Version: 0.2.1
Summary: No shit JWT implementation
Home-page: https://github.com/cordalace/nsjwt
Author: Azat Kurbanov
Author-email: cordalace@gmail.com
License: Apache License 2.0
Keywords: jwt json web token
Platform: UNKNOWN
Classifier: Development Status :: 3 - Alpha
Classifier: Intended Audience :: Developers
Classifier: License :: OSI Approved :: Apache Software License
Classifier: Programming Language :: Python :: 3.4
Classifier: Programming Language :: Python :: 3.5
Classifier: Programming Language :: Python :: 3.6
Classifier: Programming Language :: Python :: 3 :: Only
Classifier: Topic :: Software Development :: Libraries :: Python Modules
Classifier: Topic :: Internet :: WWW/HTTP :: Session
Requires-Dist: ujson
Requires-Dist: pybase64
